elita/__init__.py
elita/auth.py
elita/builds.py
elita/celeryconfig.py
elita/celeryinit.py
elita/elita_exceptions.py
elita/models.py
elita/servers.py
elita/views.py
elita/actions/__init__.py
elita/actions/action.py
elita/crypto/__init__.py
elita/crypto/keypair.py
elita/dataservice/__init__.py
elita/dataservice/datavalidator.py
elita/dataservice/models.py
elita/dataservice/mongo_service.py
elita/dataservice/root_tree.py
elita/deployment/__init__.py
elita/deployment/deploy.py
elita/deployment/gitservice.py
elita/deployment/salt_control.py
elita/deployment/sshconfig.py
elita/util/__init__.py
elita/util/type_check.py
elita-0.64.1.dist-info/DESCRIPTION.rst
elita-0.64.1.dist-info/entry_points.txt
elita-0.64.1.dist-info/METADATA
elita-0.64.1.dist-info/metadata.json
elita-0.64.1.dist-info/RECORD
elita-0.64.1.dist-info/top_level.txt
elita-0.64.1.dist-info/WHEEL
elita_cli/__init__.py
elita_cli/__init__.pyc
elita_cli/subcommands.py
elita_cli/subcommands.pyc
elita_install/__init__.py
elita_install/darwin.py
elita_install/linux.py
elita_install/util/elita.ini
elita_install/util/git_wrapper_setup.ps1
elita_install/util/init.d-defaults
elita_install/util/init.d-elita
elita_install/util/logrotate
elita_install/util/nginx.conf
elita_install/util/salt-master
