Metadata-Version: 2.0
Name: elita
Version: 0.64.1
Summary: Continuous deployment (continuous delivery) and infrastructure management REST framework
Home-page: https://bitbucket.org/scorebig/elita
Author: Benjamen Keroack
Author-email: ben@elita.io
License: Apache
Keywords: continuous deployment delivery REST automation devops
Platform: UNKNOWN
Classifier: Programming Language :: Python
Classifier: Framework :: Pyramid
Classifier: Topic :: Internet :: WWW/HTTP
Classifier: Topic :: Internet :: WWW/HTTP :: WSGI :: Application
Classifier: Topic :: System :: Systems Administration
Classifier: Topic :: Software Development :: Build Tools
Requires-Dist: pyramid
Requires-Dist: gunicorn
Requires-Dist: gevent
Requires-Dist: salt (<=2014.1.10)
Requires-Dist: celery
Requires-Dist: pymongo
Requires-Dist: glob2
Requires-Dist: gitpython (>=0.3.2.RC1)
Requires-Dist: requests
Requires-Dist: python-slugify
Requires-Dist: simplejson
Requires-Dist: PyYAML
Requires-Dist: lockfile
Requires-Dist: sh
Requires-Dist: clint
Requires-Dist: jsonpatch
Requires-Dist: nose
Requires-Dist: mock
